{"id": 352606, "author": "Ashish Cardanoscan", "title": "Testnet Cardanoscan Explorer", "url": "http://app.ideascale.com/t/UM5UZBivb", "category": 25939, "amount": 7500, "description": "IOHK dev explorer for testnet does not provide useful insights that developers need. Many developers are asking for a testnet Cardanoscan.", "no_assessments": 0, "rating": 0, "videos": [], "media": [], "solution": "Cardanoscan has lots of developer-friendly insights into the Cardano blockchain. We will make the platform available for the testnet network", "experience": "We are running the mainnet version of Cardanoscan explorer - the leading Cardano explorer"}