{"id": 352730, "author": "Rajiv Tangri", "title": "The Game of Life", "url": "http://app.ideascale.com/t/UM5UZBixd", "category": 25939, "amount": 100000, "description": "How do we get developers to develop on Cardano?", "no_assessments": 0, "rating": 0, "videos": [], "media": [], "solution": "Incentivized referral gaming. Creating a gaming system approachable to children. It looks like a game, but they are actually developing apps", "experience": "I work in healthcare and have taught critical thinkers in the field.\n\nHaving a nephew who is 12, I know what Minecraft can be."}