{"id": 383886, "author": "rin9s", "title": "\ud83d\udc51 Alternatives to Plutocracy \ud83d\udcb8", "url": "https://cardano.ideascale.com/a/dtd/383886-48088", "category": 26257, "amount": 125000, "description": "Comment pouvons-nous d\u00e9couvrir et exp\u00e9rimenter de nouveaux types de gouvernance pour aller au-del\u00e0 de \"1 pi\u00e8ce = 1 vote\" ?\nComment pouvons-nous faire \u00e9voluer notre gouvernance ?", "f6_no_assessments": 0, "f6_rating": 0, "videos": [], "media": [], "f6_assessments": [], "importance": "La gouvernance d\u00e9centralis\u00e9e est un \u00e9norme d\u00e9fi. Nous devons \u00e9tudier et tester de nouveaux syst\u00e8mes pour trouver des moyens d'aller au-del\u00e0 de la centralisation du pouvoir.", "success": "D\u00e9veloppement et test substantiel de nouveaux syst\u00e8mes de gouvernance -\nPlateformes, cadres, recherche, etc."}