{"id": 367058, "author": "", "title": "Community-Made Interactive Guides", "url": "https://cardano.ideascale.com/a/dtd/367058-48088", "category": 26113, "amount": 11500, "description": "Inexperienced entrepreneurs are not given a clear path for how to transform their ideas into businesses.", "f6_no_assessments": 0, "f6_rating": 0, "videos": [], "media": [], "solution": "Build a site for community members to run, submit, comment, and vote on routines that guide proposers through the entire business process.", "experience": "Plutus pioneer. 9 years of software development experience, a degree in Computer Science, and a background in full stack web development."}