{"id": 383959, "author": "jt.aussiegingersnap", "title": "Easy Node Deployment - [Revelar]", "url": "https://cardano.ideascale.com/a/dtd/383959-48088", "category": 26246, "amount": 5000, "description": "Pour les nouveaux FS et les d\u00e9veloppeurs, la cr\u00e9ation de n\u0153uds Cardano (non locaux) prend trop de temps.", "f6_no_assessments": 0, "f6_rating": 0, "videos": [], "media": [], "f6_assessments": [], "solution": "Cr\u00e9ez un d\u00e9ploiement de n\u0153uds simple et s\u00e9curis\u00e9 avec des configurations open source, des pratiques de s\u00e9curit\u00e9 et une surveillance.", "experience": "Une d\u00e9cennie en tant que fondateur et directeur technique d'une entreprise de technologie + pionnier de Plutus + Fonds 6 + aux c\u00f4t\u00e9s d'une \u00e9quipe compl\u00e8te d'ing\u00e9nieurs. (Voir ci-dessous)"}