{"id": 384495, "author": "erikrehbinder", "title": "new.tech circular accelerator", "url": "https://cardano.ideascale.com/a/dtd/384495-48088", "category": 26255, "amount": 500000, "description": "\u53ea\u6709\u5f53\u6211\u4eec\u5927\u89c4\u6a21\u5730\u589e\u52a0\u8d44\u91d1\u3001\u5408\u4f5c\u548c\u5faa\u73af\u521b\u65b0\u65f6\uff0c\u5168\u4e16\u754c\u7684\u53ef\u6301\u7eed\u6d88\u8d39\u624d\u4f1a\u53d1\u751f\u3002", "f6_no_assessments": 0, "f6_rating": 0, "videos": [], "media": [], "f6_assessments": [], "solution": "\u4e00\u4e2a\u5168\u7403\u793e\u533a\u548c\u6570\u5b57\u8d27\u5e01\uff0c\u5176\u4f7f\u547d\u662f\u52a0\u901f\u5faa\u73af\u5546\u4e1a\u6a21\u5f0f\u548c\u751f\u6001\u7cfb\u7edf\u3002", "experience": "\u521b\u59cb\u4eba\u62e5\u6709\u4e00\u4e2a\u6210\u529f\u7684\u5faa\u73af\u4e1a\u52a1\uff0c\u5e76\u53c2\u4e0e\u4e86\u4e16\u754c\u9886\u5148\u7684\u52a0\u901f\u5668\uff0c\u5982Katapult\u3001Antler\u548cEMNY\u3002"}