{"id": 367906, "author": "", "title": "Automated Tax Collection", "url": "https://cardano.ideascale.com/a/dtd/367906-48088", "category": 26103, "amount": 25000, "description": "Building a business on a blockchain creates a complicated tax liability\u00a0 No dAPP exists to automate tax collection or payments.", "f6_no_assessments": 0, "f6_rating": 0, "videos": [], "media": [], "solution": "My proposed solution is to develop a payment gateway for business, that separates out a percentage of revenue for tax purposes.", "experience": "Seasoned Network and Server Engineers with 40 years of combined experience."}