{"id": 368470, "author": "", "title": "Data Marketplace with AI powered", "url": "https://cardano.ideascale.com/a/dtd/368470-48088", "category": 26103, "amount": 120000, "description": "There is currently no decentralized data exchange (IDX) on Cardano and no real standards when it comes to data exchange between entities.", "f6_no_assessments": 0, "f6_rating": 0, "videos": [], "media": [], "solution": "Onvux - The first IDX in the Cardano ecosystem.\n\nEnables users and companies to restore control and monetize their data.", "experience": "Our tech team has 15+ years of experience at IT and innovative developments"}