{"id": 383186, "author": "smilerosepool", "title": "Creating a Bilingual Website Hub", "url": "https://cardano.ideascale.com/a/dtd/383186-48088", "category": 26238, "amount": 12000, "description": "No hay suficientes sitios web que conecten directamente a las comunidades de Cardano de habla inglesa y japonesa con la informaci\u00f3n y los enlaces necesarios.", "f6_no_assessments": 0, "f6_rating": 0, "videos": [], "media": [], "f6_assessments": [], "solution": "Crearemos un sitio web que albergue textos y v\u00eddeos en ambos idiomas y ofreceremos \"recompensas\" por los contenidos, junto con llamadas mensuales de Zoom.", "experience": "Ya estamos realizando reuniones mensuales de Zoom en ambos idiomas. Uno de los proponentes es un SPO en Jap\u00f3n y el otro un artista de la CNFT con sede en Estados Unidos."}