{"id": 383185, "author": "cardosco17", "title": "\ud83d\udd30 dVote - LATAM \ud83d\udd30 AtalaPRISM", "url": "https://cardano.ideascale.com/a/dtd/383185-48088", "category": 26242, "amount": 98489, "description": "The lack of a single, easily auditable platform where people can curate, present or vote on popular initiatives.", "f6_no_assessments": 0, "f6_rating": 0, "videos": [], "media": [], "f6_assessments": [], "solution": "Develop a platform with the benefits of the Cardano blockchain where citizens could submit proposals, vote or curate.", "experience": "Blockchain revolution, educator, content creator, stake pool operator, community manager, high experience working with public."}