{"id": 384687, "author": "mariacarmo369", "title": "LovelaceAcademy website Translation", "url": "https://cardano.ideascale.com/a/dtd/384687-48088", "category": 26242, "amount": 5500, "description": "\u589e\u52a0\u56fd\u9645\u793e\u4f1a\u5728\u5df4\u897f\u7684\u53c2\u4e0e", "f6_no_assessments": 0, "f6_rating": 0, "videos": [], "media": [], "f6_assessments": [], "solution": "\u7ffb\u8bd1\u6211\u4eec\u7f51\u7ad9\u7684\u4e66\u9762\u5185\u5bb9\nhttps://learn.lovelace.academy/\n\u57fa\u91d12\u4e2d\u8d44\u52a9\u7684\u63d0\u6848", "experience": "\u739b\u4e3d\u4e9a-\u5361\u5c14\u83ab 369\n\u57fa\u601d\n\u859b\u4f1f\u8fbe"}