{"id": 384191, "author": "geekship", "title": "SOIL: Semantic E-Commerce", "url": "https://cardano.ideascale.com/a/dtd/384191-48088", "category": 26247, "amount": 42, "description": "Categorizing and searching for relevant products is hard.", "f6_no_assessments": 0, "f6_rating": 0, "videos": [], "media": [], "f6_assessments": [], "solution": "The SOIL ecosystem uses crowdsourcing and AI to categorize and innovate products.", "experience": "Software developer for over 10 years, focused on frontend in the last 5.\nhttps://www.linkedin.com/in/martin-vavrovic-9617514a/"}